neuralm/__init__.py
neuralm/core/__init__.py
neuralm/core/model_builder.py
neuralm/layers/__init__.py
neuralm/layers/layer_factory.py
neuralm/models/__init__.py
neuralm/models/attention.py
neuralm/models/autoencoder.py
neuralm/models/cnn.py
neuralm/models/gan.py
neuralm/models/mlp.py
neuralm/models/rnn.py
neuralm/models/sequential.py
neuralm/models/siamese.py
neuralm/utils/__init__.py
neuralm/utils/yaml_parser.py
neuralm-0.1.1.dist-info/licenses/LICENSE
neuralm-0.1.1.dist-info/METADATA
neuralm-0.1.1.dist-info/WHEEL
neuralm-0.1.1.dist-info/top_level.txt
neuralm-0.1.1.dist-info/RECORD
